fastapi_starter/__init__.py
fastapi_starter/main.py
fastapi_starter/utils.py
fastapi_starter/templates/README.md.tmpl
fastapi_starter/templates/config.py.tmpl
fastapi_starter/templates/env.tmpl
fastapi_starter/templates/gitignore.tmpl
fastapi_starter/templates/main.py.tmpl
fastapi_starter/templates/models.py.tmpl
fastapi_starter/templates/requirements.txt.tmpl
fastapi_starter/templates/routes.py.tmpl
fastapi_starter/templates/schemas.py.tmpl
fastapi_starter/templates/services.py.tmpl
fastapi_starter/templates/test_main.py.tmpl
fastapi_pro_temp_generator-0.1.3.dist-info/METADATA
fastapi_pro_temp_generator-0.1.3.dist-info/WHEEL
fastapi_pro_temp_generator-0.1.3.dist-info/entry_points.txt
fastapi_pro_temp_generator-0.1.3.dist-info/top_level.txt
fastapi_pro_temp_generator-0.1.3.dist-info/RECORD
