Metadata-Version: 2.4
Name: fastapi-pro-temp-generator
Version: 0.1.3
Summary: A simple CLI tool to generate a clean FastAPI project structure.
Author-email: Bhavdip <lakumbhavdip555@gmail.com>
License: MIT
Project-URL: Homepage, https://github.com/lakumbhavdip/fastapi-starter
Project-URL: Bug Tracker, https://github.com/lakumbhavdip/fastapi-starter/issues
Keywords: fastapi,cli,generator,starter-kit,boilerplate
Classifier: Programming Language :: Python :: 3
Classifier: License :: OSI Approved :: MIT License
Classifier: Operating System :: OS Independent
Requires-Python: >=3.8
Requires-Dist: click>=8.0.0
